cli_code/__init__.py
cli_code/_old.py
cli_code/allmodule.py
cli_code/clI_build_check_repo2.py
cli_code/cli_conda_merge.py
cli_code/cli_convert_ipny.py
cli_code/cli_docs.py
cli_code/cli_download.py
cli_code/cli_env_autoinstall.py
cli_code/cli_git.py
cli_code/cli_github_search.py
cli_code/cli_module_parser.py
cli_code/cli_repo_check.py
cli_code/session.py
cli_code/util.py
cli_code/util_filesearch.py
cli_code/util_log.py
cli_code/cli_doc_auto/__init__.py
cli_code/cli_doc_auto/main.py
cli_code/cli_doc_auto/lib/__init__.py
cli_code/cli_doc_auto/lib/common/__init__.py
cli_code/cli_doc_auto/lib/common/argparse/__init__.py
cli_code/cli_doc_auto/lib/common/argparse/cli.py
cli_code/cli_doc_auto/pyreg/__init__.py
cli_code/cli_doc_auto/pyreg/home.py
cli_code/cli_doc_auto/pyreg/context/__init__.py
cli_code/cli_doc_auto/pyreg/context/config.py
cli_code/cli_doc_auto/pyreg/literal/__init__.py
cli_code/cli_doc_auto/pyreg/literal/cons.py
cli_code/cli_doc_auto/pyreg/manager/__init__.py
cli_code/cli_doc_auto/pyreg/manager/fs.py
cli_code/cli_doc_auto/pyreg/manager/regex.py
cli_code-28.1.0.dist-info/DESCRIPTION.rst
cli_code-28.1.0.dist-info/METADATA
cli_code-28.1.0.dist-info/RECORD
cli_code-28.1.0.dist-info/WHEEL
cli_code-28.1.0.dist-info/entry_points.txt
cli_code-28.1.0.dist-info/metadata.json
cli_code-28.1.0.dist-info/top_level.txt
