Metadata-Version: 2.0
Name: cli-code
Version: 28.1.0
Summary: long_description
Home-page: https://github.com/arita37/cli_code
Author: arita37, Kevin Noel
License: UNKNOWN
Platform: UNKNOWN
Classifier: Development Status :: 3 - Alpha
Classifier: Intended Audience :: End Users/Desktop
Classifier: Intended Audience :: Developers
Classifier: Intended Audience :: Science/Research
Classifier: License :: OSI Approved :: Apache Software License
Classifier: Programming Language :: Python :: 3
Classifier: Programming Language :: Python :: 3.6
Classifier: Topic :: Scientific/Engineering
Classifier: Topic :: Scientific/Engineering :: Artificial Intelligence
Classifier: Topic :: Software Development :: Libraries
Classifier: Topic :: Software Development :: Libraries :: Python Modules
Classifier: Topic :: Scientific/Engineering :: Information Analysis
Classifier: Environment :: Console
Classifier: Environment :: Web Environment
Classifier: Operating System :: POSIX
Classifier: Operating System :: MacOS :: MacOS X
Requires-Dist: numpy
